MANIFEST.in
README.md
setup.py
arrows_esolang/Action.py
arrows_esolang/Codegen.py
arrows_esolang/Interpreter.py
arrows_esolang/Parser.py
arrows_esolang/Statement.py
arrows_esolang/Util.py
arrows_esolang/__init__.py
arrows_esolang/library.c
arrows_esolang.egg-info/PKG-INFO
arrows_esolang.egg-info/SOURCES.txt
arrows_esolang.egg-info/dependency_links.txt
arrows_esolang.egg-info/requires.txt
arrows_esolang.egg-info/top_level.txt
bin/arrows
bin/arrowsc
test/test_compiler.py
test/test_interpreter.py