Metadata-Version: 2.1
Name: arrows-esolang
Version: 1.0.2
Summary: An esoteric language that uses drawings of arrows.
Home-page: https://github.com/JohnathonNow/arrows-esolang
Author: John Westhoff
Author-email: johnjwesthoff@gmail.com
License: UNKNOWN
Platform: UNKNOWN
